rdreceiptnotice/EcsInterface.py
rdreceiptnotice/__init__.py
rdreceiptnotice/mainModel.py
rdreceiptnotice/metadata.py
rdreceiptnotice/operation.py
rdreceiptnotice/utility.py
rdreceiptnotice-1.3.0.dist-info/METADATA
rdreceiptnotice-1.3.0.dist-info/WHEEL
rdreceiptnotice-1.3.0.dist-info/top_level.txt
rdreceiptnotice-1.3.0.dist-info/RECORD
